Metadata-Version: 2.1
Name: odoo12-addon-intrastat-product
Version: 12.0.1.0.4
Summary: Base module for Intrastat Product
Home-page: UNKNOWN
Author: brain-tec AG, Akretion, Noviat, Odoo Community Association (OCA)
Author-email: support@odoo-community.org
License: AGPL-3
Platform: UNKNOWN
Classifier: Programming Language :: Python
Classifier: Framework :: Odoo
Classifier: License :: OSI Approved :: GNU Affero General Public License v3
Requires-Python: >=3.5
Requires-Dist: odoo12-addon-intrastat-base
Requires-Dist: odoo12-addon-product-harmonized-system
Requires-Dist: odoo12-addon-report-xlsx-helper
Requires-Dist: odoo (<12.1dev,>=12.0a)
